openlp/__init__.py
openlp/utils.py
openlp3-0.1.1.dist-info/METADATA
openlp3-0.1.1.dist-info/WHEEL
openlp3-0.1.1.dist-info/top_level.txt
openlp3-0.1.1.dist-info/RECORD
