Metadata-Version: 2.1
Name: openlp3
Version: 0.1.1
Summary: OpenLP Python SDK 0.1.1
Home-page: 
Author: Midhun Chandrasekhar
Author-email: csekhar.jr@gmail.com
License: MIT
Classifier: Intended Audience :: Developers
Classifier: License :: OSI Approved :: MIT License
Classifier: Programming Language :: Python
Classifier: Programming Language :: Python :: 3
Classifier: Programming Language :: Python :: 3.6
Classifier: Programming Language :: Python :: 3.7
Classifier: Programming Language :: Python :: 3.8
Classifier: Programming Language :: Python :: 3.9
Classifier: Operating System :: OS Independent
Requires-Dist: web3
